langchain_brightdata/__init__.py
langchain_brightdata/_utilities.py
langchain_brightdata/brightdata_scraper.py
langchain_brightdata/brightdata_search.py
langchain_brightdata/brightdata_unlocker.py
langchain_brightdata-0.2.0.dist-info/METADATA
langchain_brightdata-0.2.0.dist-info/WHEEL
langchain_brightdata-0.2.0.dist-info/licenses/LICENSE
langchain_brightdata-0.2.0.dist-info/RECORD
