Metadata-Version: 2.4
Name: langchain-brightdata
Version: 0.2.0
Summary: LangChain integration for Bright Data web scraping and SERP APIs
Project-URL: Homepage, https://github.com/luminati-io/langchain-brightdata
Project-URL: Repository, https://github.com/luminati-io/langchain-brightdata
Project-URL: Documentation, https://github.com/luminati-io/langchain-brightdata#readme
Author: Meir Kadosh
License-Expression: MIT
License-File: LICENSE
Keywords: ai,bright-data,brightdata,langchain,llm,serp,web-scraping
Classifier: Development Status :: 4 - Beta
Classifier: Intended Audience :: Developers
Classifier: License :: OSI Approved :: MIT License
Classifier: Operating System :: OS Independent
Classifier: Programming Language :: Python :: 3
Classifier: Programming Language :: Python :: 3.9
Classifier: Programming Language :: Python :: 3.10
Classifier: Programming Language :: Python :: 3.11
Classifier: Programming Language :: Python :: 3.12
Classifier: Topic :: Internet :: WWW/HTTP :: Indexing/Search
Classifier: Topic :: Software Development :: Libraries :: Python Modules
Requires-Python: >=3.9
Requires-Dist: aiohttp>=3.8.0
Requires-Dist: langchain-core>=0.1.0
Requires-Dist: pydantic>=2.0.0
Requires-Dist: requests>=2.28.0
Provides-Extra: dev
Requires-Dist: black>=23.0.0; extra == 'dev'
Requires-Dist: pytest-asyncio>=0.21.0; extra == 'dev'
Requires-Dist: pytest>=7.0.0; extra == 'dev'
Requires-Dist: ruff>=0.1.0; extra == 'dev'
